README.md
setup.cfg
setup.py
python/pyrenn.py
python/pyrenn.egg-info/PKG-INFO
python/pyrenn.egg-info/SOURCES.txt
python/pyrenn.egg-info/dependency_links.txt
python/pyrenn.egg-info/requires.txt
python/pyrenn.egg-info/top_level.txt