Metadata-Version: 1.1
Name: pyrenn
Version: 0.1
Summary: A recurrent neural network toolbox for Python and Matlab.
Home-page: http://github.com/yabata/pyrenn
Author: Dennis Atabay
Author-email: dennis.atabay@gmail.com
License: GPL
Download-URL: https://github.com/yabata/pyrenn/archive/v0.1.tar.gz
Platform: UNKNOWN
Classifier: Development Status :: 5 - Production/Stable
Classifier: Intended Audience :: Developers
Classifier: Intended Audience :: Science/Research
Classifier: License :: OSI Approved :: GNU General Public License v3 (GPLv3)
Classifier: Operating System :: OS Independent
Classifier: Programming Language :: Python
Classifier: Topic :: Scientific/Engineering :: Artificial Intelligence
